{
  "warnings" : [ ],
  "files" : [ "()_rust-testcases_interprocedural_book-methods_book-methods.rs.main().json", "bool_Rectangle.can_hold(&Rectangle_self,_&Rectangle_other)_1425800145.json", "report.json" ],
  "info" : {
    "cfgs" : "3",
    "duration" : "65ms",
    "end" : "2023-02-13T15:27:33.477+01:00",
    "expressions" : "46",
    "files" : "2",
    "globals" : "2",
    "members" : "3",
    "programs" : "1",
    "start" : "2023-02-13T15:27:33.412+01:00",
    "statements" : "9",
    "units" : "2",
    "version" : "0.1b7",
    "warnings" : "0"
  },
  "configuration" : {
    "analysisGraphs" : "NONE",
    "descendingGlbThreshold" : "5",
    "descendingPhaseType" : "NONE",
    "fixpointWorkingSet" : "FIFOWorkingSet",
    "jsonOutput" : "true",
    "openCallPolicy" : "RustReturnTopPolicy",
    "semanticChecks" : "",
    "serializeInputs" : "false",
    "serializeResults" : "true",
    "syntacticChecks" : "",
    "wideningThreshold" : "5",
    "workdir" : "rust-outputs/interprocedural/book-methods"
  }
}