{"name":"() rust-testcases/cfg/simple-if/simple-if.rs::main()","description":null,"nodes":[{"id":0,"subNodes":[1,2],"text":"let mut _x : untyped = 0"},{"id":1,"text":"mut _x"},{"id":2,"text":"0"},{"id":3,"subNodes":[4,5],"text":"==(_x, 5)"},{"id":4,"text":"_x"},{"id":5,"text":"5"},{"id":6,"subNodes":[7,8],"text":"_x = 1"},{"id":7,"text":"_x"},{"id":8,"text":"1"},{"id":9,"text":"ret"}],"edges":[{"sourceId":0,"destId":3,"kind":"SequentialEdge"},{"sourceId":3,"destId":6,"kind":"TrueEdge"},{"sourceId":3,"destId":9,"kind":"FalseEdge"},{"sourceId":6,"destId":9,"kind":"SequentialEdge"}],"descriptions":[{"nodeId":0,"description":{"expressions":["_x"],"state":{"heap":"monolith","type":"noop","value":"noop"}}},{"nodeId":1,"description":{"expressions":["_x"],"state":{"heap":"monolith","type":"noop","value":"noop"}}},{"nodeId":2,"description":{"expressions":["0"],"state":{"heap":"monolith","type":"noop","value":"noop"}}},{"nodeId":3,"description":{"expressions":[],"state":{"heap":"monolith","type":"noop","value":"noop"}}},{"nodeId":4,"description":{"expressions":["_x"],"state":{"heap":"monolith","type":"noop","value":"noop"}}},{"nodeId":5,"description":{"expressions":["5"],"state":{"heap":"monolith","type":"noop","value":"noop"}}},{"nodeId":6,"description":{"expressions":["_x"],"state":{"heap":"monolith","type":"noop","value":"noop"}}},{"nodeId":7,"description":{"expressions":["_x"],"state":{"heap":"monolith","type":"noop","value":"noop"}}},{"nodeId":8,"description":{"expressions":["1"],"state":{"heap":"monolith","type":"noop","value":"noop"}}},{"nodeId":9,"description":{"expressions":["skip"],"state":{"heap":"monolith","type":"noop","value":"noop"}}}]}