{"name":"() rust-testcases/cfg/field-existance/field-existance.rs::main()","description":null,"nodes":[{"id":0,"subNodes":[1,2],"text":"let m : untyped = Message::Move{1, 2}"},{"id":1,"text":"m"},{"id":2,"subNodes":[3,4],"text":"Message::Move{1, 2}"},{"id":3,"text":"1"},{"id":4,"text":"2"},{"id":5,"subNodes":[6,7],"text":"Message::Move{x = a,y = b}=m2"},{"id":6,"text":"Message::Move{x = a,y = b}"},{"id":7,"text":"m2"},{"id":8,"subNodes":[9,10],"text":"println!(\"{}\", a)"},{"id":9,"text":"\"{}\""},{"id":10,"text":"a"},{"id":11,"subNodes":[12,13],"text":"println!(\"{}\", b)"},{"id":12,"text":"\"{}\""},{"id":13,"text":"b"},{"id":14,"text":"ret"}],"edges":[{"sourceId":0,"destId":5,"kind":"SequentialEdge"},{"sourceId":5,"destId":8,"kind":"TrueEdge"},{"sourceId":5,"destId":14,"kind":"FalseEdge"},{"sourceId":8,"destId":11,"kind":"SequentialEdge"},{"sourceId":11,"destId":14,"kind":"SequentialEdge"}],"descriptions":[{"nodeId":0,"description":{"expressions":[],"state":{"heap":"_|_","type":"noop","value":"noop"}}},{"nodeId":1,"description":{"expressions":["m"],"state":{"heap":"monolith","type":"noop","value":"noop"}}},{"nodeId":2,"description":{"expressions":[],"state":{"heap":"monolith","type":"noop","value":"noop"}}},{"nodeId":3,"description":{"expressions":["1"],"state":{"heap":"monolith","type":"noop","value":"noop"}}},{"nodeId":4,"description":{"expressions":["2"],"state":{"heap":"monolith","type":"noop","value":"noop"}}},{"nodeId":5,"description":{"expressions":[],"state":{"heap":"monolith","type":"noop","value":"noop"}}},{"nodeId":6,"description":{"expressions":["x = a,y = b"],"state":{"heap":"monolith","type":"noop","value":"noop"}}},{"nodeId":7,"description":{"expressions":["m2"],"state":{"heap":"monolith","type":"noop","value":"noop"}}},{"nodeId":8,"description":{"expressions":["open_call_ret_value@'rust-testcases/cfg/field-existance/field-existance.rs':8:25"],"state":{"heap":"monolith","type":"noop","value":"noop"}}},{"nodeId":9,"description":{"expressions":["{}"],"state":{"heap":"monolith","type":"noop","value":"noop"}}},{"nodeId":10,"description":{"expressions":["a"],"state":{"heap":"monolith","type":"noop","value":"noop"}}},{"nodeId":11,"description":{"expressions":["open_call_ret_value@'rust-testcases/cfg/field-existance/field-existance.rs':9:25"],"state":{"heap":"monolith","type":"noop","value":"noop"}}},{"nodeId":12,"description":{"expressions":["{}"],"state":{"heap":"monolith","type":"noop","value":"noop"}}},{"nodeId":13,"description":{"expressions":["b"],"state":{"heap":"monolith","type":"noop","value":"noop"}}},{"nodeId":14,"description":{"expressions":["skip"],"state":{"heap":"monolith","type":"noop","value":"noop"}}}]}