{"name":"rust-testcases/cfg/rectangle/rectangle.rs Rect::new()","description":null,"nodes":[{"id":0,"subNodes":[1],"text":"return Rect{width, height}"},{"id":1,"subNodes":[2,3],"text":"Rect{width, height}"},{"id":2,"text":"width"},{"id":3,"text":"height"}],"edges":[],"descriptions":[{"nodeId":0,"description":{"expressions":[],"state":{"heap":"_|_","type":"noop","value":"noop"}}},{"nodeId":1,"description":{"expressions":[],"state":{"heap":"monolith","type":"noop","value":"noop"}}},{"nodeId":2,"description":{"expressions":["width"],"state":{"heap":"monolith","type":"noop","value":"noop"}}},{"nodeId":3,"description":{"expressions":["height"],"state":{"heap":"monolith","type":"noop","value":"noop"}}}]}